esper/__init__.py
esper/agent.py
esper/api.py
esper/knowledge.py
esper/memory.py
esper/tools.py
esper/trace.py
esper/mscp/__init__.py
esper/mscp/chat2web3.py
esper/mscp/connector.py
esper/mscp/lib.py
esper/social/__init__.py
esper/social/bluesky.py
esper/social/discord.py
esper/social/farcaster.py
esper/social/mastodon.py
esper/social/telegram.py
esper/social/twitter.py
esper/storage/__init__.py
esper/storage/sqlite.py
esper/storage/supabase.py
esper/storage/tinydb.py
esper/utils/__init__.py
esper/utils/get_model_env.py
esper/utils/knowledge_to_prompt.py
ame_esper-0.1.2.dist-info/LICENSE
ame_esper-0.1.2.dist-info/METADATA
ame_esper-0.1.2.dist-info/WHEEL
ame_esper-0.1.2.dist-info/top_level.txt
ame_esper-0.1.2.dist-info/RECORD
